testutilz/__init__.py
testutilz/csv_reader.py
testutilz/jsoncompare.py
testutilz/listeners.py
testutilz/uniresponse_utils.py
testutilz/utilities.py
testutilz-1.0.0.dist-info/LICENSE
testutilz-1.0.0.dist-info/METADATA
testutilz-1.0.0.dist-info/WHEEL
testutilz-1.0.0.dist-info/top_level.txt
testutilz-1.0.0.dist-info/RECORD
