Metadata-Version: 2.1
Name: testutilz
Version: 1.0.0
Summary: Utilities required for performance and functional tests
Author: Zeta
License: UNKNOWN
Platform: UNKNOWN
Classifier: Programming Language :: Python :: 3
Classifier: License :: OSI Approved :: MIT License
Classifier: Operating System :: OS Independent
Requires-Python: >=3.6
License-File: LICENSE
Requires-Dist: selenium (>=4.1.0)
Requires-Dist: gevent (>=21.8.0)
Requires-Dist: geventhttpclient (>=1.5.3)
Requires-Dist: psycogreen (>=1.0.2)
Requires-Dist: locust (>=2.6.0)
Requires-Dist: requests (>=2.26.0)
Requires-Dist: jsonpath-ng (>=1.5.3)
Requires-Dist: greenlet (==1.1.2)
Requires-Dist: psycopg2-binary (>=2.9.2)
